Jadio/__init__.py
Jadio/module.py
Jadio-0.2.dist-info/LICENSE
Jadio-0.2.dist-info/METADATA
Jadio-0.2.dist-info/WHEEL
Jadio-0.2.dist-info/top_level.txt
Jadio-0.2.dist-info/RECORD
